README
setup.py
src/django_dojoserializer.egg-info/PKG-INFO
src/django_dojoserializer.egg-info/SOURCES.txt
src/django_dojoserializer.egg-info/dependency_links.txt
src/django_dojoserializer.egg-info/requires.txt
src/django_dojoserializer.egg-info/top_level.txt
src/dojoserializer/__init__.py
src/dojoserializer/models.py
src/dojoserializer/tests.py
src/dojoserializer/utils.py
src/dojoserializer/views.py
src/dojoserializer/templatetags/__init__.py
src/dojoserializer/templatetags/content_type_id_lookup.py