Metadata-Version: 1.0
Name: django-dojoserializer
Version: 1.1.2
Summary: Serializes django model instances to a dojo data compatible JSON representation
Home-page: http://code.google.com/p/django-dojoserializer
Author: Fabian Topfstedt
Author-email: myfirstname@mylastname.de
License: MIT
Platform: UNKNOWN
